xllamacpp/__init__.py
xllamacpp/_version.py
xllamacpp/xllamacpp.cpython-39-x86_64-linux-gnu.so
xllamacpp_cuda12x.libs/libgomp-b6bd0f69.so.1.0.0
xllamacpp_cuda12x-0.1.6.dist-info/LICENSE
xllamacpp_cuda12x-0.1.6.dist-info/METADATA
xllamacpp_cuda12x-0.1.6.dist-info/WHEEL
xllamacpp_cuda12x-0.1.6.dist-info/top_level.txt
xllamacpp_cuda12x-0.1.6.dist-info/RECORD
