Metadata-Version: 2.2
Name: xllamacpp-cuda12x
Version: 0.1.6
Summary: A Python wrapper of llama.cpp
Author-email: Shakeeb Alireza <me@example.org>
Requires-Python: >=3.8
License-File: LICENSE
Provides-Extra: test
Requires-Dist: pytest; extra == "test"
Requires-Dist: pytest-cov; extra == "test"
Dynamic: requires-python
